{
    "profile_info": {
        "login": "JevKnight",
        "id": 51061152,
        "node_id": "MDQ6VXNlcjUxMDYxMTUy",
        "avatar_url": "https://avatars.githubusercontent.com/u/51061152?v=4",
        "html_url": "https://github.com/JevKnight",
        "type": "User",
        "site_admin": false,
        "name": "Jewel",
        "company": "home",
        "blog": "",
        "location": "Brasil/Brazil",
        "email": null,
        "hireable": null,
        "bio": "May God guide us on this trail of blood that will form.",
        "twitter_username": null,
        "public_repos": 1,
        "public_gists": 1,
        "followers": 76,
        "following": 105,
        "created_at": "2019-05-26T20:55:12Z",
        "updated_at": "2024-05-30T21:54:37Z"
    },
    "original_repos_count": 1,
    "forked_repos_count": 0,
    "mutual_followers": [
        "OsmanMR99",
        "victorpreston",
        "warmice71",
        "mahseema",
        "JoJoDevAdventure",
        "AppServiceProvider",
        "jaayperez",
        "dongwookkim3",
        "Malihashahi",
        "cumsoft",
        "huzgrx",
        "alexica32",
        "JohnMwendwa",
        "luckyengineer053",
        "kenjinote",
        "habibfcn",
        "maruki00",
        "cosmohacker",
        "tulna07",
        "saraivais",
        "Blueberryy",
        "Sandro-BR",
        "V1nni00",
        "damthang111",
        "mdhachem",
        "milsaware",
        "Aziz-AXG",
        "Saidiislam",
        "Julius-Hamilton",
        "ValentineFernandes",
        "VictorDjun",
        "A-Ebied",
        "decoderwhoami",
        "worldlead",
        "Brightness999",
        "top0910",
        "yeasin72",
        "gamemann",
        "bluestars1233",
        "devking1116",
        "Rodrigo-Sarmento",
        "sunny0714",
        "911-carrera",
        "H-K-R",
        "IDouble",
        "CodingWithEnjoy",
        "PremChapagain",
        "thefazeelahmed",
        "somekindofwallflower",
        "lodhik9",
        "naruhitokaide",
        "Ambesawi",
        "duongminh191",
        "urmybestfriend",
        "hocinebouarara",
        "GamingAlex553",
        "D4Fi",
        "dougkalash",
        "Moneemsaadaoui",
        "krkarma777",
        "Nakshatra05",
        "Shehab-Hegab"
    ],
    "following": [
        "romulobr",
        "pythonbrasil",
        "kenjinote",
        "TheKins",
        "compiledcode83",
        "nashmuhandes",
        "sunny0714",
        "gamemann",
        "jasineri",
        "mdhachem",
        "IDouble",
        "rxrbln",
        "maruki00",
        "cosmohacker",
        "degencap777",
        "EleoXDA",
        "jishanshaikh4",
        "Moneemsaadaoui",
        "lodhik9",
        "Kwynto",
        "Brightness999",
        "Blueberryy",
        "Tomiwa-Ot",
        "top0910",
        "Saidiislam",
        "jaayperez",
        "devking1116",
        "yeasin72",
        "PremChapagain",
        "hocinebouarara",
        "AppServiceProvider",
        "themiralay",
        "fazeelkhalid",
        "caioagiani",
        "thefazeelahmed",
        "blockchainGuru1018",
        "bpradiip",
        "Rodrigo-Sarmento",
        "Kripto-Sec",
        "cezarmarcior",
        "abhizaik",
        "Sen-Takatsuki",
        "H-K-R",
        "Malihashahi",
        "peter-kimanzi",
        "mr-dev-dragon",
        "EmeraldCoasttt",
        "tulna07",
        "JohnMwendwa",
        "Aziz-AXG",
        "Berkancelik",
        "0vm",
        "ASPPIBRA",
        "cesaracjota",
        "cryptoguy55",
        "jrohitofficial",
        "darian-catalin-cucer",
        "JoJoDevAdventure",
        "mrpaziresh",
        "somekindofwallflower",
        "GamingAlex553",
        "A-Ebied",
        "mertsabinov",
        "habibfcn",
        "milsaware",
        "saraivais",
        "naruhitokaide",
        "dangalansky",
        "cumsoft",
        "VictorDjun",
        "ValentineFernandes",
        "acehood0126",
        "lssleo",
        "urmybestfriend",
        "bluestars1233",
        "xmas7",
        "luckyengineer053",
        "victorpreston",
        "eagle950108",
        "CodingWithEnjoy",
        "Sandro-BR",
        "decoderwhoami",
        "Ambesawi",
        "JyaburaniTech",
        "dawidolko",
        "OracleBrain",
        "V1nni00",
        "huzgrx",
        "Julius-Hamilton",
        "dongwookkim3",
        "alexica32",
        "worldlead",
        "warmice71",
        "Shehab-Hegab",
        "damthang111",
        "duongminh191",
        "D4Fi",
        "Nakshatra05",
        "OsmanMR99",
        "mahseema",
        "911-carrera",
        "gitechnologi",
        "krkarma777",
        "dougkalash",
        "monolab825"
    ],
    "followers": [
        "kenjinote",
        "btcguru77",
        "sunny0714",
        "gamemann",
        "mustafacagri",
        "mdhachem",
        "IDouble",
        "maruki00",
        "cosmohacker",
        "Moneemsaadaoui",
        "lodhik9",
        "Brightness999",
        "chipnertkj",
        "Blueberryy",
        "top0910",
        "Saidiislam",
        "jaayperez",
        "devking1116",
        "yeasin72",
        "PremChapagain",
        "hocinebouarara",
        "AppServiceProvider",
        "ogunsoladebayo",
        "thefazeelahmed",
        "Rodrigo-Sarmento",
        "qpeckin",
        "H-K-R",
        "Malihashahi",
        "tulna07",
        "OfficialCodeVoyage",
        "JohnMwendwa",
        "Aziz-AXG",
        "Charles-Chrismann",
        "JoJoDevAdventure",
        "somekindofwallflower",
        "GamingAlex553",
        "A-Ebied",
        "habibfcn",
        "milsaware",
        "saraivais",
        "naruhitokaide",
        "cumsoft",
        "VictorDjun",
        "ValentineFernandes",
        "urmybestfriend",
        "bluestars1233",
        "luckyengineer053",
        "victorpreston",
        "CodingWithEnjoy",
        "Sandro-BR",
        "decoderwhoami",
        "Ambesawi",
        "V1nni00",
        "huzgrx",
        "RamonLarcherRibeiro",
        "Julius-Hamilton",
        "dongwookkim3",
        "alexica32",
        "worldlead",
        "warmice71",
        "Shehab-Hegab",
        "damthang111",
        "duongminh191",
        "D4Fi",
        "Nakshatra05",
        "OsmanMR99",
        "psharifi1997",
        "mahseema",
        "911-carrera",
        "seniorvuejsdeveloper",
        "krkarma777",
        "dougkalash",
        "nobbydoo80",
        "GrayMamoru",
        "jeweljev",
        "xopaz"
    ],
    "repo_list": [
        "JevKnight"
    ],
    "forked_repo_list": [],
    "unique_emails": {
        "reno.games.673@gmail.com": {
            "name": "JevLsk",
            "commits": [
                "7bc5339337118dd4cdd996cb03b56f5b56d5a658",
                "2594c6cbcd9249e53d0087a114adce17b3c4917e",
                "4fe6156ca173f157bd1a5059ea7b76fbd2c3eb93",
                "bdc5c7686cbe32e63eeeafe90122070407eaf6ba",
                "5465dcfd02aa54098a56133adb206cfaee8af00b",
                "711d572547c09a8731f367aef1db1010cc0c833f",
                "bfbc47cd4ef1e6b3acf5b6cc43506078f3c7f856",
                "ebcc9a7cfbec63d243e33cfe76ca305cdbe64ed8",
                "b2a1f4372b193ba4ae0b2f586aabe924cb56fd13",
                "2b715aa06578f8c4fcfedc8192a15c336c06a56c",
                "7d709ec5b7fcb118c56658630b4eb71696b6ad4a",
                "6dc9363882a4eb9b90bded64338bcf383fc7c025",
                "2906ea044721afdaba77806fbd20a80aac1b61bc",
                "f12590a53b040a0d1c455b8f1119e88f734f2300",
                "5b1dadf5a0af70a5da9d3c95490c15c747a04a60",
                "847897ffeca1351a59a56c39078ba3003465da37",
                "da94fda96644da91e8fe61c2c8cda16572a67125",
                "b48a447af20ecc9c152259c8bd1ddabf51602049",
                "03a30a1614d4dc5d29ff66d598ed5de201d64eb4",
                "c54b6a6cbcce58f38030d9a57bc93d219d026fd2",
                "c87db94864adfd16ce3a8ee7a5f58c322ae21810",
                "923d8e23a82be4899879ba4fbbd33cfd19a63710",
                "aff35e126e0aa75e60a584e780dbc54222b881c5",
                "7318b17f19f222345a3a4b70a6c56655baa7b5b2",
                "fb94c58b54e0e92703087179957a42fcb413da13",
                "84b08559950de17c3f985d50b4595bed84f44b24",
                "5bcede987dd5c5033aad9fea465b95a21adbb7ff",
                "df3c6481c0a69159caf001a77043bb5d0f12beb0",
                "8c8d440e4a5ae6ce3eb55315312d7097162713b0",
                "60b79c465093b555a2776066da71236f474c2740",
                "ba1a9ac6b3f4598cad44a747c6d05f04179934b4",
                "c927164f1c4d8690674c42c51ee1411b6e296c04",
                "6c3108177ef9741ca823ef298b1674631d4e7fcf",
                "8f7088fd15bfcf59ec71d4d76ee96b0a91b2c82f",
                "56162b164f4b8313939550390676f607b19fcd78",
                "9147121a0512f3d195826ebc4efeb7c3c8de5d12",
                "c476f2547dea32810e7cb2eb02c22dd14468ba38",
                "84ef38767dc28275f17ae19a72b1004cb20bcc8d",
                "234bac655487ff05af8a117ebece53a0e75fd59a",
                "4f319e17783b95322c9d9f816b79a6df24275f37",
                "69e69a26b47b792c80b2cb7231c9cd9b3ec30728",
                "eba464252bd886e1227f86517a9539e791b91ab3",
                "4ddb6b67c924ab8bc3be2fcef5adc803f7029b2a",
                "19434304021705c7fbec29087d88228f6998c1f9",
                "4672adfb7e609a119d9e1681fde698079cccf7b4",
                "021fe35780434d390de1d038b391975e6e4bba81",
                "aa9b991a6e4a2a64f1c44a7bea7f1050271d98e4",
                "dd2a3c6a9dcedef030b96aceccea34c0e8bcbef4",
                "124a4e00324e140180a4abb42c27cc904d639b04",
                "78ef711634ea71e49b03de3ddd34b425a1d4af8d"
            ]
        },
        "51061152+JevLsk@users.noreply.github.com": {
            "name": "JevLsk - The Knight",
            "commits": [
                "45fb84f6ef55ac30c20023b746e99d31d9e1fe44",
                "7c7a46affb4da1c7021ba16bb0b5664ef8428fce",
                "218ab5c10b1c7e42c2d948e524de9861a5cf367a",
                "5790111ddcbf9d8d29d307e96cff1c6e63464f34",
                "e64ee9251f88cd00f73472bf8e9242fc13e69513"
            ]
        },
        "noreply@github.com": {
            "name": "GitHub",
            "commits": [
                "45fb84f6ef55ac30c20023b746e99d31d9e1fe44",
                "7c7a46affb4da1c7021ba16bb0b5664ef8428fce",
                "218ab5c10b1c7e42c2d948e524de9861a5cf367a",
                "5790111ddcbf9d8d29d307e96cff1c6e63464f34",
                "e64ee9251f88cd00f73472bf8e9242fc13e69513"
            ]
        }
    },
    "contributors": {
        "JevKnight": [
            "JevKnight"
        ]
    },
    "pull_requests_to_other_repos": {},
    "commits_to_other_repos": {}
}